sqs_admin/__init__.py
sqs_admin/app.py
sqs_admin/extension.py
sqs_admin/util.py
sqs_admin/bin/.gitkeep
sqs_admin/bin/darwin-amd64/sqs-admin
sqs_admin/bin/darwin-arm64/sqs-admin
sqs_admin/bin/dist/favicon.ico
sqs_admin/bin/dist/index.html
sqs_admin/bin/dist/manifest.json
sqs_admin/bin/dist/robots.txt
sqs_admin/bin/dist/assets/main.Bd6O3Oyf.js
sqs_admin/bin/dist/assets/mui.CqQUs1S2.js
sqs_admin/bin/dist/assets/vendor.2bcXEMx6.js
sqs_admin/bin/linux-amd64/sqs-admin
sqs_admin/bin/linux-arm64/sqs-admin
sqs_admin-0.8.1.dist-info/METADATA
sqs_admin-0.8.1.dist-info/WHEEL
sqs_admin-0.8.1.dist-info/entry_points.txt
sqs_admin-0.8.1.dist-info/top_level.txt
sqs_admin-0.8.1.dist-info/RECORD
