Metadata-Version: 2.2
Name: sqs-admin
Version: 0.8.1
Summary: LocalStack Extension: SQS-Admin
Author-email: Pascal Euhus <pascal.euhus@gmx.de>
License: Apache-2.0
Project-URL: Homepage, https://github.com/pacovk/sqs-admin
Keywords: localstack,localstack-extension,extension
Requires-Python: >=3.8
Requires-Dist: botocore
Requires-Dist: rolo
Requires-Dist: boto3
Requires-Dist: jsonpatch
Requires-Dist: cookiecutter
Provides-Extra: dev
Requires-Dist: localstack>=0.0.0.dev; extra == "dev"
